gaia_python_sdk_atlas/atlas_client.py
gaia_python_sdk_atlas/atlas_client_builder.py
gaia_python_sdk_atlas/atlas_request.py
gaia_python_sdk_atlas/atlas_response.py
gaia_python_sdk_atlas/main.py
gaia_python_sdk_atlas-0.2.0.dist-info/WHEEL
gaia_python_sdk_atlas-0.2.0.dist-info/METADATA
gaia_python_sdk_atlas-0.2.0.dist-info/RECORD
